pyrprimos/__init__.py
pyrprimos-1.0.dist-info/LICENSE.txt
pyrprimos-1.0.dist-info/METADATA
pyrprimos-1.0.dist-info/WHEEL
pyrprimos-1.0.dist-info/top_level.txt
pyrprimos-1.0.dist-info/RECORD
